mcp_everythingcloudplatform/__init__.py
mcp_everythingcloudplatform/main.py
mcp_everythingcloudplatform-0.1.1.dist-info/METADATA
mcp_everythingcloudplatform-0.1.1.dist-info/WHEEL
mcp_everythingcloudplatform-0.1.1.dist-info/entry_points.txt
mcp_everythingcloudplatform-0.1.1.dist-info/top_level.txt
mcp_everythingcloudplatform-0.1.1.dist-info/RECORD
