Metadata-Version: 2.4
Name: mcp_everythingcloudplatform
Version: 0.1.1
Summary: MCP Demo Everything Cloud Platform
Author: Jai Chenchlani
Dynamic: author
Dynamic: summary
